LICENSE
temperature_conversion/__init__.py
temperature_conversion/convert.py
temperature_conversion-1.0.0.dist-info/LICENSE
temperature_conversion-1.0.0.dist-info/WHEEL
temperature_conversion-1.0.0.dist-info/METADATA
temperature_conversion-1.0.0.dist-info/RECORD
