Metadata-Version: 2.1
Name: temperature-conversion
Version: 1.0.0
Summary: Paquete de conversión de temperaturas
Home-page: https://github.com/odmendoza/temperature_conversion
License: MIT
Keywords: temperature conversion,kelvin,fahrenheit,rankine
Author: Danilo Mendoza
Author-email: odmendoza@utpl.edu.ec
Requires-Python: >=3.7,<4.0
Classifier: License :: OSI Approved :: MIT License
Classifier: Programming Language :: Python :: 3
Classifier: Programming Language :: Python :: 3.7
Classifier: Programming Language :: Python :: 3.8
Classifier: Programming Language :: Python :: 3.9
Project-URL: Repository, https://github.com/odmendoza/temperature_conversion
